.gitignore
.travis.yml
CHANGES.txt
CONTRIBUTORS.txt
MANIFEST.in
README.rst
bootstrap.py
buildout.cfg
setup.py
travis.cfg
collective/__init__.py
collective.themeswitcher.egg-info/PKG-INFO
collective.themeswitcher.egg-info/SOURCES.txt
collective.themeswitcher.egg-info/dependency_links.txt
collective.themeswitcher.egg-info/entry_points.txt
collective.themeswitcher.egg-info/namespace_packages.txt
collective.themeswitcher.egg-info/not-zip-safe
collective.themeswitcher.egg-info/requires.txt
collective.themeswitcher.egg-info/top_level.txt
collective/themeswitcher/SkinsTool.py
collective/themeswitcher/ThemeTransform.py
collective/themeswitcher/__init__.py
collective/themeswitcher/configure.zcml
collective/themeswitcher/switcher.py
collective/themeswitcher/testing.py
collective/themeswitcher/upgrades.py
collective/themeswitcher/upgrades.zcml
collective/themeswitcher/profiles/default/metadata.xml
collective/themeswitcher/profiles/default/registry.xml
collective/themeswitcher/tests/__init__.py
collective/themeswitcher/tests/base.py
collective/themeswitcher/tests/fake.py
collective/themeswitcher/tests/test_setup.py
collective/themeswitcher/tests/test_switcher.py
docs/LICENSE.txt